SecLoad/__init__.py
SecLoad/apihandlers.py
SecLoad/enums.py
SecLoad-1.0.1.dist-info/METADATA
SecLoad-1.0.1.dist-info/WHEEL
SecLoad-1.0.1.dist-info/license.txt
SecLoad-1.0.1.dist-info/top_level.txt
SecLoad-1.0.1.dist-info/RECORD
