Metadata-Version: 2.1
Name: SecLoad
Version: 1.0.1
Summary: SecLoad SDK package for Roblox Script Builder APIs.
Author: equsjd
Keywords: roblox
Classifier: Development Status :: 5 - Production/Stable
Classifier: Programming Language :: Python :: 3
License-File: license.txt
Requires-Dist: requests-html
Requires-Dist: lxml-html-clean
